{"version": 0.6, "generator": "Overpass API 0.7.61.5 4133829e", "osm3s": {"timestamp_osm_base": "2023-11-05T19:18:39Z", "copyright": "The data included in this document is from www.openstreetmap.org. The data is made available under ODbL."}, "elements": [{"type": "node", "id": 102249602, "lat": 43.5877366, "lon": 13.5175782}, {"type": "node", "id": 102249603, "lat": 43.5864453, "lon": 13.5172552}, {"type": "node", "id": 102249604, "lat": 43.5849298, "lon": 13.5170759}, {"type": "node", "id": 102249605, "lat": 43.58496, "lon": 13.5166824}, {"type": "node", "id": 102249606, "lat": 43.5845434, "lon": 13.5166411}, {"type": "node", "id": 102249608, "lat": 43.5845564, "lon": 13.5159843}, {"type": "node", "id": 102249609, "lat": 43.5845765, "lon": 13.5141187}, {"type": "node", "id": 102249611, "lat": 43.5851343, "lon": 13.5117441}, {"type": "node", "id": 102249617, "lat": 43.5865533, "lon": 13.51327}, {"type": "node", "id": 102249619, "lat": 43.5891706, "lon": 13.5145815}, {"type": "node", "id": 102249620, "lat": 43.5893593, "lon": 13.5149025}, {"type": "node", "id": 102249621, "lat": 43.5889115, "lon": 13.5158528}, {"type": "node", "id": 102249622, "lat": 43.5891097, "lon": 13.51606}, {"type": "node", "id": 102249623, "lat": 43.5887064, "lon": 13.5167473}, {"type": "node", "id": 102249625, "lat": 43.588178, "lon": 13.5173465}, {"type": "node", "id": 267110333, "lat": 43.5861712, "lon": 13.5167265, "tags": {"amenity": "fountain"}}, {"type": "node", "id": 267287334, "lat": 43.5883687, "lon": 13.5140258}, {"type": "node", "id": 267287335, "lat": 43.5882767, "lon": 13.5146539}, {"type": "node", "id": 267287336, "lat": 43.5889689, "lon": 13.5151153}, {"type": "node", "id": 267287820, "lat": 43.5857521, "lon": 13.5149243}, {"type": "node", "id": 267287821, "lat": 43.5854177, "lon": 13.516576}, {"type": "node", "id": 267287822, "lat": 43.5858111, "lon": 13.5166003}, {"type": "node", "id": 267287823, "lat": 43.5859618, "lon": 13.5161521}, {"type": "node", "id": 267287824, "lat": 43.5860101, "lon": 13.5155472}, {"type": "node", "id": 267287826, "lat": 43.5862013, "lon": 13.5149666}, {"type": "node", "id": 267287828, "lat": 43.5864873, "lon": 13.5146576}, {"type": "node", "id": 267287829, "lat": 43.5869535, "lon": 13.5139453}, {"type": "node", "id": 267287830, "lat": 43.5872135, "lon": 13.5137269}, {"type": "node", "id": 267287831, "lat": 43.5871523, "lon": 13.5135794}, {"type": "node", "id": 267287832, "lat": 43.5868851, "lon": 13.5138165}, {"type": "node", "id": 267287833, "lat": 43.5863691, "lon": 13.514589}, {"type": "node", "id": 267287834, "lat": 43.5860769, "lon": 13.5148636}, {"type": "node", "id": 267287835, "lat": 43.5859775, "lon": 13.5149237}, {"type": "node", "id": 267287837, "lat": 43.5858842, "lon": 13.5149323}, {"type": "node", "id": 267288005, "lat": 43.5854633, "lon": 13.5155369}, {"type": "node", "id": 281002647, "lat": 43.5863087, "lon": 13.5170087, "tags": {"barrier": "gate"}}, {"type": "node", "id": 281002683, "lat": 43.5878728, "lon": 13.5174479, "tags": {"barrier": "gate", "foot": "yes"}}, {"type": "node", "id": 281002762, "lat": 43.5893318, "lon": 13.5148405, "tags": {"barrier": "gate"}}, {"type": "node", "id": 281002810, "lat": 43.5874832, "lon": 13.5137325, "tags": {"barrier": "gate"}}, {"type": "node", "id": 309026327, "lat": 43.5865872, "lon": 13.5134874, "tags": {"barrier": "gate"}}, {"type": "node", "id": 310207436, "lat": 43.5853497, "lon": 13.5163768}, {"type": "node", "id": 525555506, "lat": 43.5868655, "lon": 13.5171894, "tags": {"addr:city": "Ancona", "addr:housenumber": "12", "addr:postcode": "60131", "addr:street": "Via delle Brecce Bianche", "amenity": "cafe", "name": "Bar Ingegneria", "operator": "FSC Food Srl", "ref:vatin": "IT02767640424"}}, {"type": "node", "id": 637004899, "lat": 43.5868967, "lon": 13.5166821, "tags": {"amenity": "bank", "atm": "yes", "name": "Unicredit Ancona Universit\u00e0", "opening_hours": "Mo-Fr 09:00-12:00", "operator": "Unicredit"}}, {"type": "node", "id": 637004900, "lat": 43.5885023, "lon": 13.5150685, "tags": {"amenity": "cafe", "name": "Bar Agraria - Sirio spa"}}, {"type": "node", "id": 683708916, "lat": 43.586188, "lon": 13.5170412}, {"type": "node", "id": 683708929, "lat": 43.5862258, "lon": 13.5169592}, {"type": "node", "id": 683708933, "lat": 43.5862837, "lon": 13.5170102}, {"type": "node", "id": 683708982, "lat": 43.5883964, "lon": 13.5171111}, {"type": "node", "id": 684439510, "lat": 43.5871104, "lon": 13.5154966, "tags": {"addr:city": "Ancona", "addr:housenumber": "12", "addr:postcode": "60131", "addr:street": "Via delle Brecce Bianche", "alt_name": "Centro di ateneo di documentazione - Polo di Monte Dago", "amenity": "library", "email": "info.bibliotecsci@univpm.it", "internet_access": "wlan", "name": "Biblioteca Tecnico-Scientifica-Biomedica", "opening_hours": "Mo-Fr 08:30-19:15; Sa 08:30-13:00", "phone": "+39 071 220 4701", "website": "https://cad.univpm.it/SebinaOpac/library/Tecnico-Scientifica-Biomedica/UANBU", "wheelchair": "yes"}}, {"type": "node", "id": 685562295, "lat": 43.5853532, "lon": 13.5122876}, {"type": "node", "id": 685562298, "lat": 43.5852997, "lon": 13.5117769}, {"type": "node", "id": 685562301, "lat": 43.5851742, "lon": 13.5117535, "tags": {"barrier": "gate", "bicycle": "no", "foot": "no", "name": "Cancello di emergenza"}}, {"type": "node", "id": 685562304, "lat": 43.5847956, "lon": 13.515432}, {"type": "node", "id": 685562307, "lat": 43.5846924, "lon": 13.5154185}, {"type": "node", "id": 685562309, "lat": 43.5846533, "lon": 13.5156997}, {"type": "node", "id": 685562311, "lat": 43.5847524, "lon": 13.515744}, {"type": "node", "id": 685562313, "lat": 43.584732, "lon": 13.5154165}, {"type": "node", "id": 685562315, "lat": 43.5854202, "lon": 13.5156747}, {"type": "node", "id": 685562317, "lat": 43.5853945, "lon": 13.5158112}, {"type": "node", "id": 685562321, "lat": 43.5848375, "lon": 13.5164119}, {"type": "node", "id": 685562323, "lat": 43.5846868, "lon": 13.515898}, {"type": "node", "id": 685562324, "lat": 43.5846944, "lon": 13.5160475}, {"type": "node", "id": 685562326, "lat": 43.5847063, "lon": 13.5162677}, {"type": "node", "id": 685562327, "lat": 43.5847259, "lon": 13.5164314}, {"type": "node", "id": 685562329, "lat": 43.5847593, "lon": 13.5164892}, {"type": "node", "id": 685562330, "lat": 43.5848151, "lon": 13.5164121}, {"type": "node", "id": 685562332, "lat": 43.5847886, "lon": 13.5162908}, {"type": "node", "id": 685562333, "lat": 43.584797, "lon": 13.5158941}, {"type": "node", "id": 685562334, "lat": 43.584973, "lon": 13.5159724}, {"type": "node", "id": 685562335, "lat": 43.5848574, "lon": 13.5159487}, {"type": "node", "id": 685562336, "lat": 43.5849218, "lon": 13.5164101}, {"type": "node", "id": 685562337, "lat": 43.5848695, "lon": 13.5164094, "tags": {"barrier": "lift_gate"}}, {"type": "node", "id": 685562339, "lat": 43.5853851, "lon": 13.5159593}, {"type": "node", "id": 685562340, "lat": 43.585398, "lon": 13.516061}, {"type": "node", "id": 685562341, "lat": 43.5853633, "lon": 13.5162335}, {"type": "node", "id": 685562342, "lat": 43.584952, "lon": 13.5170283}, {"type": "node", "id": 685562343, "lat": 43.5849871, "lon": 13.5166121}, {"type": "node", "id": 685562345, "lat": 43.5853072, "lon": 13.5166591}, {"type": "node", "id": 685562346, "lat": 43.5852939, "lon": 13.5170337}, {"type": "node", "id": 685562349, "lat": 43.5865245, "lon": 13.5133448}, {"type": "node", "id": 685562351, "lat": 43.5866239, "lon": 13.5135607}, {"type": "node", "id": 685562353, "lat": 43.5867751, "lon": 13.5133524}, {"type": "node", "id": 685562354, "lat": 43.5855424, "lon": 13.515067}, {"type": "node", "id": 685562356, "lat": 43.5857711, "lon": 13.5151798}, {"type": "node", "id": 685562357, "lat": 43.5856519, "lon": 13.5151328}, {"type": "node", "id": 685562358, "lat": 43.5857397, "lon": 13.5151018}, {"type": "node", "id": 685562360, "lat": 43.5858368, "lon": 13.5151134}, {"type": "node", "id": 685562363, "lat": 43.5861175, "lon": 13.5150706}, {"type": "node", "id": 685562365, "lat": 43.5859967, "lon": 13.5151622}, {"type": "node", "id": 685562366, "lat": 43.585886, "lon": 13.5151857}, {"type": "node", "id": 685562369, "lat": 43.5859448, "lon": 13.5151071}, {"type": "node", "id": 685562371, "lat": 43.5861479, "lon": 13.5150081}, {"type": "node", "id": 685562373, "lat": 43.5855252, "lon": 13.5152142}, {"type": "node", "id": 685562375, "lat": 43.5856818, "lon": 13.5153223}, {"type": "node", "id": 685562377, "lat": 43.5858333, "lon": 13.5153636}, {"type": "node", "id": 685562379, "lat": 43.5858003, "lon": 13.5155726}, {"type": "node", "id": 685562380, "lat": 43.5856573, "lon": 13.5155679}, {"type": "node", "id": 685562383, "lat": 43.5856235, "lon": 13.5157334}, {"type": "node", "id": 685562385, "lat": 43.5856862, "lon": 13.5158647}, {"type": "node", "id": 685562387, "lat": 43.5861558, "lon": 13.5152811}, {"type": "node", "id": 685562388, "lat": 43.5860087, "lon": 13.5153376}, {"type": "node", "id": 685562390, "lat": 43.5859988, "lon": 13.515727}, {"type": "node", "id": 685562393, "lat": 43.5860045, "lon": 13.5158596}, {"type": "node", "id": 685562395, "lat": 43.5858755, "lon": 13.5157569}, {"type": "node", "id": 685562403, "lat": 43.5873035, "lon": 13.5140449}, {"type": "node", "id": 685562406, "lat": 43.5872981, "lon": 13.5143684}, {"type": "node", "id": 685562409, "lat": 43.5875623, "lon": 13.5138193}, {"type": "node", "id": 685562410, "lat": 43.5881383, "lon": 13.5138717}, {"type": "node", "id": 685562417, "lat": 43.5881756, "lon": 13.5139021, "tags": {"barrier": "gate", "bicycle": "no", "foot": "no", "name": "Cancello di emergenza"}}, {"type": "node", "id": 685562435, "lat": 43.587802, "lon": 13.5146013}, {"type": "node", "id": 685562444, "lat": 43.5856167, "lon": 13.5160439}, {"type": "node", "id": 685562446, "lat": 43.5856527, "lon": 13.5161399}, {"type": "node", "id": 685562448, "lat": 43.5855596, "lon": 13.5163243}, {"type": "node", "id": 685562450, "lat": 43.5857809, "lon": 13.5163537}, {"type": "node", "id": 685562454, "lat": 43.5860068, "lon": 13.5160437}, {"type": "node", "id": 685562455, "lat": 43.5859079, "lon": 13.5163244}, {"type": "node", "id": 685562457, "lat": 43.5858849, "lon": 13.5164267}, {"type": "node", "id": 685562489, "lat": 43.5870598, "lon": 13.5171047}, {"type": "node", "id": 685562490, "lat": 43.5873106, "lon": 13.5171815}, {"type": "node", "id": 685562512, "lat": 43.587257, "lon": 13.5174612, "tags": {"barrier": "gate", "name": "Ingresso disabili"}}, {"type": "node", "id": 685562515, "lat": 43.5870314, "lon": 13.517279}, {"type": "node", "id": 685562516, "lat": 43.5872821, "lon": 13.5173559}, {"type": "node", "id": 685604783, "lat": 43.5853172, "lon": 13.5134863, "tags": {"amenity": "parking", "layer": "-1", "parking": "underground"}}, {"type": "node", "id": 685963906, "lat": 43.5851725, "lon": 13.5170874, "tags": {"barrier": "gate"}}, {"type": "node", "id": 685963919, "lat": 43.5851735, "lon": 13.5170122}, {"type": "node", "id": 685963920, "lat": 43.5851268, "lon": 13.5170444}, {"type": "node", "id": 704961547, "lat": 43.5870086, "lon": 13.5144378}, {"type": "node", "id": 704961548, "lat": 43.5863191, "lon": 13.5157133}, {"type": "node", "id": 704961553, "lat": 43.5869096, "lon": 13.5147831}, {"type": "node", "id": 704961554, "lat": 43.5867005, "lon": 13.5149196}, {"type": "node", "id": 704961555, "lat": 43.5868036, "lon": 13.5149447}, {"type": "node", "id": 704961556, "lat": 43.5868554, "lon": 13.5146227}, {"type": "node", "id": 704961557, "lat": 43.5863752, "lon": 13.5162058}, {"type": "node", "id": 704961558, "lat": 43.5864068, "lon": 13.5154082}, {"type": "node", "id": 704961559, "lat": 43.5866434, "lon": 13.5152573}, {"type": "node", "id": 704961562, "lat": 43.5854838, "lon": 13.5155396, "tags": {"barrier": "bollard", "bicycle": "yes", "foot": "yes"}}, {"type": "node", "id": 704961563, "lat": 43.5863286, "lon": 13.5156235}, {"type": "node", "id": 704961564, "lat": 43.5867262, "lon": 13.5154399}, {"type": "node", "id": 704961566, "lat": 43.5868006, "lon": 13.5147259}, {"type": "node", "id": 704961567, "lat": 43.5864953, "lon": 13.5154268}, {"type": "node", "id": 704961568, "lat": 43.5869475, "lon": 13.514847}, {"type": "node", "id": 704961570, "lat": 43.5869531, "lon": 13.5144211}, {"type": "node", "id": 704961571, "lat": 43.5855493, "lon": 13.5152311, "tags": {"barrier": "bollard", "bicycle": "yes", "foot": "yes"}}, {"type": "node", "id": 704961572, "lat": 43.5862982, "lon": 13.516147}, {"type": "node", "id": 704961576, "lat": 43.5865907, "lon": 13.5152344}, {"type": "node", "id": 712778947, "lat": 43.5878126, "lon": 13.5167163}, {"type": "node", "id": 712778948, "lat": 43.5881832, "lon": 13.5168851}, {"type": "node", "id": 712778954, "lat": 43.5880836, "lon": 13.5170719}, {"type": "node", "id": 712778955, "lat": 43.5882006, "lon": 13.5167874}, {"type": "node", "id": 712778957, "lat": 43.5879014, "lon": 13.5168117}, {"type": "node", "id": 712778959, "lat": 43.5880927, "lon": 13.516829}, {"type": "node", "id": 712778962, "lat": 43.5881704, "lon": 13.5169629}, {"type": "node", "id": 712778965, "lat": 43.5880878, "lon": 13.5168658}, {"type": "node", "id": 712778968, "lat": 43.5878225, "lon": 13.5169207}, {"type": "node", "id": 712778970, "lat": 43.5877785, "lon": 13.5172137}, {"type": "node", "id": 712778972, "lat": 43.5878562, "lon": 13.5172321}, {"type": "node", "id": 712778973, "lat": 43.5882073, "lon": 13.5161417}, {"type": "node", "id": 712778975, "lat": 43.5883047, "lon": 13.5161707}, {"type": "node", "id": 712778977, "lat": 43.587783, "lon": 13.5168935}, {"type": "node", "id": 712778979, "lat": 43.5878312, "lon": 13.5173318}, {"type": "node", "id": 712778985, "lat": 43.5880546, "lon": 13.5170537}, {"type": "node", "id": 736987455, "lat": 43.5886466, "lon": 13.516649}, {"type": "node", "id": 736987461, "lat": 43.5880385, "lon": 13.5143924}, {"type": "node", "id": 736987466, "lat": 43.5883942, "lon": 13.5167396}, {"type": "node", "id": 736987467, "lat": 43.5866679, "lon": 13.5153442}, {"type": "node", "id": 736987477, "lat": 43.5884818, "lon": 13.5157324}, {"type": "node", "id": 736987484, "lat": 43.5876679, "lon": 13.5157702}, {"type": "node", "id": 736987489, "lat": 43.5857561, "lon": 13.515346}, {"type": "node", "id": 736987490, "lat": 43.5885016, "lon": 13.5164381}, {"type": "node", "id": 736987509, "lat": 43.589271, "lon": 13.5147034}, {"type": "node", "id": 736987510, "lat": 43.5890468, "lon": 13.5160121}, {"type": "node", "id": 736987515, "lat": 43.5877379, "lon": 13.5157944}, {"type": "node", "id": 736987520, "lat": 43.5886081, "lon": 13.5164381}, {"type": "node", "id": 736987537, "lat": 43.5887867, "lon": 13.5165482}, {"type": "node", "id": 736987541, "lat": 43.5879539, "lon": 13.5143239}, {"type": "node", "id": 736987546, "lat": 43.5859291, "lon": 13.5153637}, {"type": "node", "id": 736987548, "lat": 43.5884788, "lon": 13.5163246}, {"type": "node", "id": 736987556, "lat": 43.5888217, "lon": 13.5162179}, {"type": "node", "id": 736987571, "lat": 43.5889796, "lon": 13.5159419}, {"type": "node", "id": 736987574, "lat": 43.5878386, "lon": 13.5154076}, {"type": "node", "id": 736987580, "lat": 43.5887336, "lon": 13.5158539}, {"type": "node", "id": 736987588, "lat": 43.588614, "lon": 13.5157209}, {"type": "node", "id": 736987596, "lat": 43.5889856, "lon": 13.516251}, {"type": "node", "id": 736987599, "lat": 43.5878721, "lon": 13.5145374}, {"type": "node", "id": 736987607, "lat": 43.5885605, "lon": 13.5157606}, {"type": "node", "id": 736987611, "lat": 43.5858148, "lon": 13.5160693}, {"type": "node", "id": 736987629, "lat": 43.5890446, "lon": 13.5161269}, {"type": "node", "id": 736987630, "lat": 43.5860836, "lon": 13.515313}, {"type": "node", "id": 736987632, "lat": 43.5882921, "lon": 13.5167839}, {"type": "node", "id": 736987638, "lat": 43.5880151, "lon": 13.514338}, {"type": "node", "id": 736987656, "lat": 43.5886058, "lon": 13.5165644}, {"type": "node", "id": 736987659, "lat": 43.5879188, "lon": 13.5149826}, {"type": "node", "id": 736987660, "lat": 43.5888874, "lon": 13.5159218}, {"type": "node", "id": 736987666, "lat": 43.5886884, "lon": 13.5157552}, {"type": "node", "id": 736987667, "lat": 43.5882833, "lon": 13.5168746}, {"type": "node", "id": 736987669, "lat": 43.5863227, "lon": 13.5159271}, {"type": "node", "id": 736987672, "lat": 43.5848284, "lon": 13.516168}, {"type": "node", "id": 736987681, "lat": 43.5877437, "lon": 13.5153693}, {"type": "node", "id": 736987686, "lat": 43.5890609, "lon": 13.5160641}, {"type": "node", "id": 1502309642, "lat": 43.5841444, "lon": 13.5158512}, {"type": "node", "id": 1502309644, "lat": 43.5843595, "lon": 13.5146741}, {"type": "node", "id": 1502309646, "lat": 43.5844338, "lon": 13.5146953}, {"type": "node", "id": 1502309677, "lat": 43.5849066, "lon": 13.5137934}, {"type": "node", "id": 1502309694, "lat": 43.5851732, "lon": 13.512124}, {"type": "node", "id": 1502309740, "lat": 43.5858465, "lon": 13.5165163}, {"type": "node", "id": 4268483943, "lat": 43.5877984, "lon": 13.5167631}, {"type": "node", "id": 5794025806, "lat": 43.5893269, "lon": 13.5148294, "tags": {"barrier": "gate"}}, {"type": "node", "id": 9695380487, "lat": 43.5854237, "lon": 13.5140705}, {"type": "node", "id": 9695380488, "lat": 43.5855965, "lon": 13.512804}, {"type": "node", "id": 9695380489, "lat": 43.5853879, "lon": 13.5140612}, {"type": "node", "id": 9695380490, "lat": 43.5855606, "lon": 13.5127947}, {"type": "node", "id": 9695397028, "lat": 43.5861326, "lon": 13.51708, "tags": {"barrier": "gate"}}, {"type": "node", "id": 9695397030, "lat": 43.5861031, "lon": 13.5172101}, {"type": "node", "id": 9695397031, "lat": 43.5861307, "lon": 13.5171959}, {"type": "node", "id": 9695397032, "lat": 43.5861423, "lon": 13.5171662}, {"type": "node", "id": 9695397033, "lat": 43.5863873, "lon": 13.5171949}, {"type": "node", "id": 9695397034, "lat": 43.586348, "lon": 13.517113}, {"type": "node", "id": 9695397035, "lat": 43.5861157, "lon": 13.5170917}, {"type": "node", "id": 9695397036, "lat": 43.5863432, "lon": 13.5170065}, {"type": "node", "id": 10647547443, "lat": 43.5882379, "lon": 13.5161508}, {"type": "way", "id": 11479866, "nodes": [102249603, 9695397033, 9695397034, 9695397036, 281002647, 683708933, 683708929, 683708916, 9695397028, 9695397035, 9695397032, 9695397031, 9695397030, 685963906, 102249604, 102249605, 102249606, 102249608, 1502309642, 1502309644, 1502309646, 102249609, 1502309677, 1502309694, 102249611, 685562301, 685562298, 685562295, 102249617, 685562349, 309026327, 685562351, 685562353, 281002810, 685562409, 685562403, 685562406, 685562435, 685562410, 685562417, 267287334, 267287335, 267287336, 102249619, 736987509, 5794025806, 281002762, 102249620, 102249621, 102249622, 102249623, 683708982, 102249625, 281002683, 102249602, 685562512, 102249603], "tags": {"amenity": "university", "name": "Universit\u00e0 Politecnica delle Marche - Polo \"Alfredo Trifogli\" Monte Dago", "name:start_date": "2019-05-14", "old_name": "Universit\u00e0 Politecnica delle Marche - Polo di Monte Dago"}}, {"type": "way", "id": 24587248, "nodes": [685562354, 685562373, 704961571, 685562375, 736987489, 685562377, 736987546, 685562388, 736987630, 685562387, 685562363, 685562365, 685562366, 685562356, 685562357, 685562354], "tags": {"amenity": "parking", "name": "P10", "parking": "surface"}}, {"type": "way", "id": 54419466, "nodes": [685562390, 267287824, 685562379, 685562380, 704961562, 267288005, 685562315, 685562383, 685562395, 685562390], "tags": {"amenity": "parking", "name": "P9", "parking": "surface"}}, {"type": "way", "id": 54419467, "nodes": [685562317, 685562339, 685562444, 736987611, 685562454, 685562393, 685562385, 685562317], "tags": {"amenity": "parking", "name": "P7", "parking": "surface"}}, {"type": "way", "id": 54419468, "nodes": [685562455, 267287823, 685562446, 685562340, 685562341, 685562448, 685562450, 685562455], "tags": {"amenity": "parking", "name": "P6", "parking": "surface"}}, {"type": "way", "id": 54419469, "nodes": [310207436, 267287821, 267287822, 1502309740, 685562457, 310207436], "tags": {"amenity": "parking", "name": "P5", "parking": "surface"}}, {"type": "way", "id": 54419471, "nodes": [685562345, 685562346, 685963919, 685963920, 685562342, 685562343, 685562345], "tags": {"amenity": "parking", "name": "P2", "parking": "surface"}}, {"type": "way", "id": 54419472, "nodes": [685562334, 685562335, 736987672, 685562321, 685562337, 685562336, 685562334], "tags": {"amenity": "parking", "name": "P4", "parking": "surface"}}, {"type": "way", "id": 54419473, "nodes": [685562304, 685562313, 685562307, 685562309, 685562323, 685562324, 685562326, 685562327, 685562329, 685562330, 685562332, 685562333, 685562311, 685562304], "tags": {"amenity": "parking", "name": "P3", "parking": "surface"}}, {"type": "way", "id": 54419477, "nodes": [267287826, 267287828, 267287829, 267287830, 267287831, 267287832, 267287833, 267287834, 267287835, 267287837, 267287820, 685562358, 685562360, 685562369, 685562371, 267287826], "tags": {"amenity": "parking", "name": "P12", "parking": "surface"}}, {"type": "way", "id": 54419492, "nodes": [685562516, 685562515, 685562489, 685562490, 685562516], "tags": {"access": "private", "amenity": "parking", "name": "P1", "parking": "surface"}}, {"type": "way", "id": 56174421, "nodes": [704961555, 704961564, 736987467, 704961559, 704961576, 704961554, 704961555], "tags": {"amenity": "parking", "name": "P11", "parking": "surface"}}, {"type": "way", "id": 56174431, "nodes": [704961568, 704961547, 704961570, 704961556, 704961566, 704961553, 704961568], "tags": {"amenity": "parking", "name": "P13", "parking": "surface"}}, {"type": "way", "id": 56174433, "nodes": [704961558, 704961563, 704961548, 736987669, 704961572, 704961557, 704961567, 704961558], "tags": {"amenity": "parking", "name": "P8", "parking": "surface"}}, {"type": "way", "id": 57275092, "nodes": [712778975, 10647547443, 712778973, 712778959, 712778965, 712778985, 712778954, 712778962, 712778948, 712778955, 712778975], "tags": {"access": "yes", "amenity": "parking", "fee": "no", "name": "P16", "parking": "surface"}}, {"type": "way", "id": 57275111, "nodes": [712778979, 712778970, 712778968, 712778977, 4268483943, 712778947, 712778957, 712778972, 712778979], "tags": {"amenity": "parking", "name": "P19", "parking": "surface"}}, {"type": "way", "id": 59433720, "nodes": [736987588, 736987490, 736987520, 736987580, 736987666, 736987588], "tags": {"amenity": "parking", "name": "P17", "parking": "surface"}}, {"type": "way", "id": 59433723, "nodes": [736987638, 736987541, 736987599, 736987681, 736987484, 736987515, 736987574, 736987659, 736987461, 736987638], "tags": {"amenity": "parking", "name": "P15", "parking": "surface"}}, {"type": "way", "id": 59433730, "nodes": [736987660, 736987556, 736987656, 736987455, 736987537, 736987596, 736987629, 736987686, 736987510, 736987571, 736987660], "tags": {"amenity": "parking", "name": "P17A", "parking": "surface"}}, {"type": "way", "id": 59433747, "nodes": [736987477, 736987632, 736987667, 736987466, 736987548, 736987607, 736987477], "tags": {"amenity": "parking", "name": "P18", "parking": "surface"}}, {"type": "way", "id": 1055110776, "nodes": [9695380489, 9695380487, 9695380488, 9695380490, 9695380489], "tags": {"amenity": "parking", "fee": "no", "orientation": "perpendicular", "parking": "street_side", "surface": "asphalt"}}]}